{
  "garden": {
    "w": 9.5,
    "d": 9.5,
    "walls": {
      "x0": 6.3,
      "xb": 2.4,
      "y0": 6.3,
      "yt": 2.4
    },
    "north": 178
  },
  "loc": {
    "lat": 48.4636,
    "lon": 8.4111
  },
  "dateStr": "2026-06-27",
  "timeMin": 674,
  "showLabels": true,
  "ref": {
    "corner": 2,
    "ox": 0,
    "oy": 0,
    "oz": 0
  },
  "points": [
    {
      "x": 0,
      "y": 0,
      "h": 2.9
    },
    {
      "x": -7,
      "y": 0,
      "h": 3
    },
    {
      "x": -9.5,
      "y": 0,
      "h": 3
    },
    {
      "x": -6.2,
      "y": -9.5,
      "h": 2.4
    },
    {
      "x": 0,
      "y": -9.5,
      "h": 2.4
    },
    {
      "x": 2.5,
      "y": 7.5,
      "h": 3
    }
  ],
  "sails": [
    {
      "on": true,
      "shape": 3,
      "bw": 5.8,
      "bl": 3.6,
      "a": 5,
      "b": 5,
      "c": 7,
      "dx": 1.2868314808985237,
      "dz": -0.7441931775259615,
      "posts": [
        4,
        0,
        2
      ],
      "color": "#c0392b",
      "opacity": 1
    },
    {
      "on": false,
      "shape": 3,
      "bw": 3,
      "bl": 3,
      "a": 3,
      "b": 3,
      "c": 3,
      "dx": -0.5338480130976946,
      "dz": 0.8526257948434761,
      "posts": [
        1,
        3,
        4
      ],
      "color": "#2c6fbb",
      "opacity": 1
    }
  ],
  "furniture": {
    "table": {
      "on": true,
      "x": -2.7527390952459085,
      "y": -4.37908062646546,
      "yaw": 0,
      "tw": 0.9,
      "tl": 1.58,
      "th": 0.74
    },
    "chair1": {
      "on": true,
      "x": -2.9305071385166768,
      "y": -3.6133698799620877,
      "yaw": 90
    },
    "chair2": {
      "on": true,
      "x": -1.7993745567905344,
      "y": -3.606782007046153,
      "yaw": -90
    },
    "pergola": {
      "on": true,
      "x": -8.2,
      "y": -3.7,
      "yaw": 0,
      "pw": 2.9,
      "pl": 2.9,
      "ph": 2.4
    }
  },
  "_pivotCorner": true,
  "person": {
    "on": true,
    "x": -2.884993394138167,
    "y": -6.996325351835675,
    "h": 1.9
  },
  "shadeAnalysis": {
    "window": "10:00–18:00",
    "date": "2026-06-27",
    "stepMin": 15,
    "perSail": [
      {
        "sail": 1,
        "integral_m2h": 83.24,
        "avg_m2": 10.41
      }
    ],
    "total_m2h": 83.24,
    "total_avg_m2": 10.41
  }
}